pyentz_package/__init__.py
pyentz_package/pyentz.py
pyentz-1.0.0.dist-info/LICENSE.txt
pyentz-1.0.0.dist-info/METADATA
pyentz-1.0.0.dist-info/WHEEL
pyentz-1.0.0.dist-info/top_level.txt
pyentz-1.0.0.dist-info/RECORD
