Metadata-Version: 2.1
Name: pyentz
Version: 1.0.0
Summary: This package is built for data scientists/analysts who needs to clean data, and train machine learning / AI models alot. The features in it are critical for Xgboost and Lightgbm models.
Home-page: https://github.com/entzyeung/pyentz
Author: Lorentz Yeung
Author-email: lorentzyeung@gmail.com
Classifier: Programming Language :: Python :: 3
Classifier: License :: OSI Approved :: MIT License
Classifier: Operating System :: OS Independent
Requires-Python: >=3.8.12
License-File: LICENSE.txt
